cs-552/shifter1.v
module shifter1 (In, Op, Go, Out);
	input [15:0] In;
	input [1:0]  Op;
	input Go;
	output [15:0] Out;
	reg [15:0] tmp;
	always@(In, Op) case (Op)
		// Rotate left
		2'b00: begin 
			tmp = In << 1;
			tmp[0] = In[15];
		end
		// Shift left
		2'b01: tmp = In << 1;

		// Arithmetic shift right
		2'b10: begin
			tmp = In >> 1;
			tmp[15] = In[15];
		end
		// Shift right
		2'b11: tmp = In >> 1;
	endcase

	assign Out = Go ? tmp : In;
endmodule

cs-552/shifter2.v
module shifter2 (In, Op, Go, Out);
	input [15:0] In;
	input [1:0]  Op;
	input Go;
	output [15:0] Out;
	wire [15:0] tmp, tmp2;

	shifter1 s0 (In, Op, Go, tmp);
	shifter1 s1 (tmp, Op, Go, tmp2);
	assign Out = Go ? tmp2 : In;
endmodule

cs-552/hw2_2/shifter4.v
module shifter4 (In, Op, Go, Out);
	input [15:0] In;
	input [1:0]  Op;
	input Go;
	output [15:0] Out;
	wire [15:0] tmp, tmp2;

	shifter2 s0 (In, Op, Go, tmp);
	shifter2 s1 (tmp, Op, Go, tmp2);
	assign Out = Go ? tmp2 : In;
endmodule

cs-552/project/shifter8.v
module shifter8 (In, Op, Go, Out);
	input [15:0] In;
	input [1:0]  Op;
	input Go;
	output [15:0] Out;
	wire [15:0] tmp, tmp2;

	shifter4 s0 (In, Op, Go, tmp);
	shifter4 s1 (tmp, Op, Go, tmp2);
	assign Out = Go ? tmp2 : In;
endmodule

cs 552/shifter.v
module shifter (In, Cnt, Op, Out);
   input [15:0] In;
   input [3:0]  Cnt;
   input [1:0]  Op;
   output [15:0] Out;
   wire [15:0] 	 oneTwo, twoFour, fourEight, eightOut;

   shifter1 s1 (In, Op, Cnt[0], oneTwo);
   shifter2 s2 (oneTwo, Op, Cnt[1], twoFour);
   shifter4 s4 (twoFour, Op, Cnt[2], fourEight);
   shifter8 s8 (fourEight, Op, Cnt[3], eightOut);
   assign Out = eightOut;
endmodule

cs 552/project/clkrst.v
/* $Author: karu $ */
/* $LastChangedDate: 2009-03-04 23:09:45 -0600 (Wed, 04 Mar 2009) $ */
/* $Rev: 45 $ */
// clock and reset generator
// CS/ECE 552
// Andy Phelps (TA)
// 3/22/06

// Clock period is 100 time units, and reset length
// to 201 time units (two rising edges of clock).

module clkrst (clk, rst, err);

    output clk;
    output rst;
    input  err;

    reg clk;
    reg rst;
    integer cycle_count;

    initial begin
      $dumpvars;
      cycle_count = 0;
      rst = 1;
      clk = 1;
      #201 rst = 0; // delay until slightly after two clock periods
    end

    always #5000 begin   // delay 1/2 clock period each time thru loop
      clk = ~clk;
      if (clk & err) begin
        $display("Error signal asserted");
        $stop;
      end
    end
    always @(posedge clk) begin
    	cycle_count = cycle_count + 1;
	if (cycle_count > 100000) begin
		$display("hmm....more than 100000 cycles of simulation...error?\n");
		$finish;
	end
    end


endmodule
// DUMMY LINE FOR REV CONTROL :0:

cs 552/hw2_1/tb_shifter.v
module tb_shifter(/*AUTOARG*/);


   /*AUTOREGINPUT*/
   // Beginning of automatic reg inputs (for undeclared instantiated-module inputs)
   reg [3:0]            Cnt;                    // To s0 of shifter.v
   reg [15:0]           In;                     // To s0 of shifter.v
   reg [1:0]            Op;                     // To s0 of shifter.v
   reg                  err;                    // To c0 of clkrst.v
   // End of automatics
   integer              cycle_count;

   wire [15:0]          Out;
                
   wire                 clk;
   wire                 rst;


   clkrst c0(/*AUTOINST*/
             // Outputs
             .clk                       (clk),
             .rst                       (rst),
             // Inputs
             .err                       (err));

   shifter s0(/*AUTOINST*/
              // Outputs
              .Out                      (Out[15:0]),
              // Inputs
              .In                       (In[15:0]),
              .Cnt                      (Cnt[3:0]),
              .Op                       (Op[1:0]));

   initial begin
      cycle_count = 0;
      In = 16'b1000000100110000;
      Cnt = 4'b1000;
      Op = 2'b10;
      $dumpvars;
      $display("Simulating 10 cycles");
   end

   always @(posedge clk) begin
      $display("Cycle %d", c0.cycle_count);

      In = In + 1;
      #3;
      $display("In: %b, Cnt: %d, Out: %b\n",
               In, Cnt, Out);
      
      if (c0.cycle_count > 10) begin
         $finish;
         
      end

   end
   
endmodule // tb_shifter

cs 552/dump.vcd
$date
	Thu Feb 10 15:19:42 2011
$end
$version
	Icarus Verilog
$end
$timescale
	1s
$end
$scope module tb_shifter $end
$var wire 16 ! Out [15:0] $end
$var wire 1 " clk $end
$var wire 1 # rst $end
$var reg 4 $ Cnt [3:0] $end
$var reg 16 % In [15:0] $end
$var reg 2 & Op [1:0] $end
$var reg 32 ' cycle_count [31:0] $end
$var reg 1 ( err $end
$scope module c0 $end
$var wire 1 ) err $end
$var reg 1 * clk $end
$var reg 32 + cycle_count [31:0] $end
$var reg 1 , rst $end
$upscope $end
$scope module s0 $end
$var wire 4 - Cnt [3:0] $end
$var wire 16 . In [15:0] $end
$var wire 2 / Op [1:0] $end
$var wire 16 0 Out [15:0] $end
$var wire 16 1 eightOut [15:0] $end
$var wire 16 2 fourEight [15:0] $end
$var wire 16 3 oneTwo [15:0] $end
$var wire 16 4 twoFour [15:0] $end
$scope module s1 $end
$var wire 1 5 Go $end
$var wire 16 6 In [15:0] $end
$var wire 2 7 Op [1:0] $end
$var wire 16 8 Out [15:0] $end
$var reg 16 9 tmp [15:0] $end
$upscope $end
$scope module s2 $end
$var wire 1 : Go $end
$var wire 16 ; In [15:0] $end
$var wire 2 < Op [1:0] $end
$var wire 16 = Out [15:0] $end
$var wire 16 > tmp [15:0] $end
$var wire 16 ? tmp2 [15:0] $end
$scope module s0 $end
$var wire 1 : Go $end
$var wire 16 @ In [15:0] $end
$var wire 2 A Op [1:0] $end
$var wire 16 B Out [15:0] $end
$var reg 16 C tmp [15:0] $end
$upscope $end
$scope module s1 $end
$var wire 1 : Go $end
$var wire 16 D In [15:0] $end
$var wire 2 E Op [1:0] $end
$var wire 16 F Out [15:0] $end
$var reg 16 G tmp [15:0] $end
$upscope $end
$upscope $end
$scope module s4 $end
$var wire 1 H Go $end
$var wire 16 I In [15:0] $end
$var wire 2 J Op [1:0] $end
$var wire 16 K Out [15:0] $end
$var wire 16 L tmp [15:0] $end
$var wire 16 M tmp2 [15:0] $end
$scope module s0 $end
$var wire 1 H Go $end
$var wire 16 N In [15:0] $end
$var wire 2 O Op [1:0] $end
$var wire 16 P Out [15:0] $end
$var wire 16 Q tmp [15:0] $end
$var wire 16 R tmp2 [15:0] $end
$scope module s0 $end
$var wire 1 H Go $end
$var wire 16 S In [15:0] $end
$var wire 2 T Op [1:0] $end
$var wire 16 U Out [15:0] $end
$var reg 16 V tmp [15:0] $end
$upscope $end
$scope module s1 $end
$var wire 1 H Go $end
$var wire 16 W In [15:0] $end
$var wire 2 X Op [1:0] $end
$var wire 16 Y Out [15:0] $end
$var reg 16 Z tmp [15:0] $end
$upscope $end
$upscope $end
$scope module s1 $end
$var wire 1 H Go $end
$var wire 16 [ In [15:0] $end
$var wire 2 \ Op [1:0] $end
$var wire 16 ] Out [15:0] $end
$var wire 16 ^ tmp [15:0] $end
$var wire 16 _ tmp2 [15:0] $end
$scope module s0 $end
$var wire 1 H Go $end
$var wire 16 ` In [15:0] $end
$var wire 2 a Op [1:0] $end
$var wire 16 b Out [15:0] $end
$var reg 16 c tmp [15:0] $end
$upscope $end
$scope module s1 $end
$var wire 1 H Go $end
$var wire 16 d In [15:0] $end
$var wire 2 e Op [1:0] $end
$var wire 16 f Out [15:0] $end
$var reg 16 g tmp [15:0] $end
$upscope $end
$upscope $end
$upscope $end
$scope module s8 $end
$var wire 1 h Go $end
$var wire 16 i In [15:0] $end
$var wire 2 j Op [1:0] $end
$var wire 16 k Out [15:0] $end
$var wire 16 l tmp [15:0] $end
$var wire 16 m tmp2 [15:0] $end
$scope module s0 $end
$var wire 1 h Go $end
$var wire 16 n In [15:0] $end
$var wire 2 o Op [1:0] $end
$var wire 16 p Out [15:0] $end
$var wire 16 q tmp [15:0] $end
$var wire 16 r tmp2 [15:0] $end
$scope module s0 $end
$var wire 1 h Go $end
$var wire 16 s In [15:0] $end
$var wire 2 t Op [1:0] $end
$var wire 16 u Out [15:0] $end
$var wire 16 v tmp [15:0] $end
$var wire 16 w tmp2 [15:0] $end
$scope module s0 $end
$var wire 1 h Go $end
$var wire 16 x In [15:0] $end
$var wire 2 y Op [1:0] $end
$var wire 16 z Out [15:0] $end
$var reg 16 { tmp [15:0] $end
$upscope $end
$scope module s1 $end
$var wire 1 h Go $end
$var wire 16 | In [15:0] $end
$var wire 2 } Op [1:0] $end
$var wire 16 ~ Out [15:0] $end
$var reg 16 !" tmp [15:0] $end
$upscope $end
$upscope $end
$scope module s1 $end
$var wire 1 h Go $end
$var wire 16 "" In [15:0] $end
$var wire 2 #" Op [1:0] $end
$var wire 16 $" Out [15:0] $end
$var wire 16 %" tmp [15:0] $end
$var wire 16 &" tmp2 [15:0] $end
$scope module s0 $end
$var wire 1 h Go $end
$var wire 16 '" In [15:0] $end
$var wire 2 (" Op [1:0] $end
$var wire 16 )" Out [15:0] $end
$var reg 16 *" tmp [15:0] $end
$upscope $end
$scope module s1 $end
$var wire 1 h Go $end
$var wire 16 +" In [15:0] $end
$var wire 2 ," Op [1:0] $end
$var wire 16 -" Out [15:0] $end
$var reg 16 ." tmp [15:0] $end
$upscope $end
$upscope $end
$upscope $end
$scope module s1 $end
$var wire 1 h Go $end
$var wire 16 /" In [15:0] $end
$var wire 2 0" Op [1:0] $end
$var wire 16 1" Out [15:0] $end
$var wire 16 2" tmp [15:0] $end
$var wire 16 3" tmp2 [15:0] $end
$scope module s0 $end
$var wire 1 h Go $end
$var wire 16 4" In [15:0] $end
$var wire 2 5" Op [1:0] $end
$var wire 16 6" Out [15:0] $end
$var wire 16 7" tmp [15:0] $end
$var wire 16 8" tmp2 [15:0] $end
$scope module s0 $end
$var wire 1 h Go $end
$var wire 16 9" In [15:0] $end
$var wire 2 :" Op [1:0] $end
$var wire 16 ;" Out [15:0] $end
$var reg 16 <" tmp [15:0] $end
$upscope $end
$scope module s1 $end
$var wire 1 h Go $end
$var wire 16 =" In [15:0] $end
$var wire 2 >" Op [1:0] $end
$var wire 16 ?" Out [15:0] $end
$var reg 16 @" tmp [15:0] $end
$upscope $end
$upscope $end
$scope module s1 $end
$var wire 1 h Go $end
$var wire 16 A" In [15:0] $end
$var wire 2 B" Op [1:0] $end
$var wire 16 C" Out [15:0] $end
$var wire 16 D" tmp [15:0] $end
$var wire 16 E" tmp2 [15:0] $end
$scope module s0 $end
$var wire 1 h Go $end
$var wire 16 F" In [15:0] $end
$var wire 2 G" Op [1:0] $end
$var wire 16 H" Out [15:0] $end
$var reg 16 I" tmp [15:0] $end
$upscope $end
$scope module s1 $end
$var wire 1 h Go $end
$var wire 16 J" In [15:0] $end
$var wire 2 K" Op [1:0] $end
$var wire 16 L" Out [15:0] $end
$var reg 16 M" tmp [15:0] $end
$upscope $end
$upscope $end
$upscope $end
$upscope $end
$upscope $end
$upscope $end
$scope module tb_shifter $end
$scope module c0 $end
$upscope $end
$scope module s0 $end
$scope module s1 $end
$upscope $end
$scope module s2 $end
$scope module s0 $end
$upscope $end
$scope module s1 $end
$upscope $end
$upscope $end
$scope module s4 $end
$scope module s0 $end
$scope module s0 $end
$upscope $end
$scope module s1 $end
$upscope $end
$upscope $end
$scope module s1 $end
$scope module s0 $end
$upscope $end
$scope module s1 $end
$upscope $end
$upscope $end
$upscope $end
$scope module s8 $end
$scope module s0 $end
$scope module s0 $end
$scope module s0 $end
$upscope $end
$scope module s1 $end
$upscope $end
$upscope $end
$scope module s1 $end
$scope module s0 $end
$upscope $end
$scope module s1 $end
$upscope $end
$upscope $end
$upscope $end
$scope module s1 $end
$scope module s0 $end
$scope module s0 $end
$upscope $end
$scope module s1 $end
$upscope $end
$upscope $end
$scope module s1 $end
$scope module s0 $end
$upscope $end
$scope module s1 $end
$upscope $end
$upscope $end
$upscope $end
$upscope $end
$upscope $end
$upscope $end
$enddefinitions $end
#0
$dumpvars
b1111111110000001 M"
b1111111110000001 L"
b10 K"
b1111111100000010 J"
b1111111100000010 I"
b1111111100000010 H"
b10 G"
b1111111000000100 F"
b1111111110000001 E"
b1111111100000010 D"
b1111111110000001 C"
b10 B"
b1111111000000100 A"
b1111111000000100 @"
b1111111000000100 ?"
b10 >"
b1111110000001001 ="
b1111110000001001 <"
b1111110000001001 ;"
b10 :"
b1111100000010011 9"
b1111111000000100 8"
b1111110000001001 7"
b1111111000000100 6"
b10 5"
b1111100000010011 4"
b1111111110000001 3"
b1111111000000100 2"
b1111111110000001 1"
b10 0"
b1111100000010011 /"
b1111100000010011 ."
b1111100000010011 -"
b10 ,"
b1111000000100110 +"
b1111000000100110 *"
b1111000000100110 )"
b10 ("
b1110000001001100 '"
b1111100000010011 &"
b1111000000100110 %"
b1111100000010011 $"
b10 #"
b1110000001001100 ""
b1110000001001100 !"
b1110000001001100 ~
b10 }
b1100000010011000 |
b1100000010011000 {
b1100000010011000 z
b10 y
b1000000100110000 x
b1110000001001100 w
b1100000010011000 v
b1110000001001100 u
b10 t
b1000000100110000 s
b1111100000010011 r
b1110000001001100 q
b1111100000010011 p
b10 o
b1000000100110000 n
b1111111110000001 m
b1111100000010011 l
b1111111110000001 k
b10 j
b1000000100110000 i
1h
b1100000010011000 g
b1000000100110000 f
b10 e
b1000000100110000 d
b1100000010011000 c
b1000000100110000 b
b10 a
b1000000100110000 `
b1000000100110000 _
b1000000100110000 ^
b1000000100110000 ]
b10 \
b1000000100110000 [
b1100000010011000 Z
b1000000100110000 Y
b10 X
b1000000100110000 W
b1100000010011000 V
b1000000100110000 U
b10 T
b1000000100110000 S
b1000000100110000 R
b1000000100110000 Q
b1000000100110000 P
b10 O
b1000000100110000 N
b1000000100110000 M
b1000000100110000 L
b1000000100110000 K
b10 J
b1000000100110000 I
0H
b1100000010011000 G
b1000000100110000 F
b10 E
b1000000100110000 D
b1100000010011000 C
b1000000100110000 B
b10 A
b1000000100110000 @
b1000000100110000 ?
b1000000100110000 >
b1000000100110000 =
b10 <
b1000000100110000 ;
0:
b1100000010011000 9
b1000000100110000 8
b10 7
b1000000100110000 6
05
b1000000100110000 4
b1000000100110000 3
b1000000100110000 2
b1111111110000001 1
b1111111110000001 0
b10 /
b1000000100110000 .
b1000 -
1,
b0 +
1*
x)
x(
b0 '
b10 &
b1000000100110000 %
b1000 $
1#
1"
b1111111110000001 !
$end
#50
0*
0"
#100
b1000000100110001 _
b1000000100110001 f
b1100000010011000 g
b1100000010011000 {
b1000000100110001 M
b1000000100110001 ]
b1000000100110001 ^
b1000000100110001 b
b1000000100110001 d
b1100000010011000 c
b1000000100110001 R
b1000000100110001 Y
b1100000010011000 Z
b1000000100110001 2
b1000000100110001 K
b1000000100110001 i
b1000000100110001 n
b1000000100110001 s
b1000000100110001 x
b1000000100110001 L
b1000000100110001 P
b1000000100110001 [
b1000000100110001 `
b1000000100110001 Q
b1000000100110001 U
b1000000100110001 W
b1100000010011000 V
b1000000100110001 ?
b1000000100110001 F
b1100000010011000 G
b1000000100110001 4
b1000000100110001 =
b1000000100110001 I
b1000000100110001 N
b1000000100110001 S
b1000000100110001 >
b1000000100110001 B
b1000000100110001 D
b1100000010011000 C
b1100000010011000 9
b1000000100110001 3
b1000000100110001 8
b1000000100110001 ;
b1000000100110001 @
b1 +
b1000000100110001 %
b1000000100110001 .
b1000000100110001 6
1*
1"
#150
0*
0"
#200
b1110000001001100 !"
b1100000010011001 v
b1100000010011001 z
b1100000010011001 |
b1000000100110010 _
b1000000100110010 f
b1100000010011001 g
b1100000010011001 {
b1000000100110010 M
b1000000100110010 ]
b1000000100110010 ^
b1000000100110010 b
b1000000100110010 d
b1100000010011001 c
b1000000100110010 R
b1000000100110010 Y
b1100000010011001 Z
b1000000100110010 2
b1000000100110010 K
b1000000100110010 i
b1000000100110010 n
b1000000100110010 s
b1000000100110010 x
b1000000100110010 L
b1000000100110010 P
b1000000100110010 [
b1000000100110010 `
b1000000100110010 Q
b1000000100110010 U
b1000000100110010 W
b1100000010011001 V
b1000000100110010 ?
b1000000100110010 F
b1100000010011001 G
b1000000100110010 4
b1000000100110010 =
b1000000100110010 I
b1000000100110010 N
b1000000100110010 S
b1000000100110010 >
b1000000100110010 B
b1000000100110010 D
b1100000010011001 C
b1100000010011001 9
b1000000100110010 3
b1000000100110010 8
b1000000100110010 ;
b1000000100110010 @
b10 +
b1000000100110010 %
b1000000100110010 .
b1000000100110010 6
1*
1"
#201
0,
0#
#250
0*
0"
#300
b1000000100110011 _
b1000000100110011 f
b1100000010011001 g
b1100000010011001 {
b1000000100110011 M
b1000000100110011 ]
b1000000100110011 ^
b1000000100110011 b
b1000000100110011 d
b1100000010011001 c
b1000000100110011 R
b1000000100110011 Y
b1100000010011001 Z
b1000000100110011 2
b1000000100110011 K
b1000000100110011 i
b1000000100110011 n
b1000000100110011 s
b1000000100110011 x
b1000000100110011 L
b1000000100110011 P
b1000000100110011 [
b1000000100110011 `
b1000000100110011 Q
b1000000100110011 U
b1000000100110011 W
b1100000010011001 V
b1000000100110011 ?
b1000000100110011 F
b1100000010011001 G
b1000000100110011 4
b1000000100110011 =
b1000000100110011 I
b1000000100110011 N
b1000000100110011 S
b1000000100110011 >
b1000000100110011 B
b1000000100110011 D
b1100000010011001 C
b1100000010011001 9
b1000000100110011 3
b1000000100110011 8
b1000000100110011 ;
b1000000100110011 @
b11 +
b1000000100110011 %
b1000000100110011 .
b1000000100110011 6
1*
1"
#350
0*
0"
#400
b1111000000100110 *"
b1110000001001101 q
b1110000001001101 u
b1110000001001101 ""
b1110000001001101 '"
b1110000001001101 w
b1110000001001101 ~
b1110000001001101 !"
b1100000010011010 v
b1100000010011010 z
b1100000010011010 |
b1000000100110100 _
b1000000100110100 f
b1100000010011010 g
b1100000010011010 {
b1000000100110100 M
b1000000100110100 ]
b1000000100110100 ^
b1000000100110100 b
b1000000100110100 d
b1100000010011010 c
b1000000100110100 R
b1000000100110100 Y
b1100000010011010 Z
b1000000100110100 2
b1000000100110100 K
b1000000100110100 i
b1000000100110100 n
b1000000100110100 s
b1000000100110100 x
b1000000100110100 L
b1000000100110100 P
b1000000100110100 [
b1000000100110100 `
b1000000100110100 Q
b1000000100110100 U
b1000000100110100 W
b1100000010011010 V
b1000000100110100 ?
b1000000100110100 F
b1100000010011010 G
b1000000100110100 4
b1000000100110100 =
b1000000100110100 I
b1000000100110100 N
b1000000100110100 S
b1000000100110100 >
b1000000100110100 B
b1000000100110100 D
b1100000010011010 C
b1100000010011010 9
b1000000100110100 3
b1000000100110100 8
b1000000100110100 ;
b1000000100110100 @
b100 +
b1000000100110100 %
b1000000100110100 .
b1000000100110100 6
1*
1"
#450
0*
0"
#500
b1000000100110101 _
b1000000100110101 f
b1100000010011010 g
b1100000010011010 {
b1000000100110101 M
b1000000100110101 ]
b1000000100110101 ^
b1000000100110101 b
b1000000100110101 d
b1100000010011010 c
b1000000100110101 R
b1000000100110101 Y
b1100000010011010 Z
b1000000100110101 2
b1000000100110101 K
b1000000100110101 i
b1000000100110101 n
b1000000100110101 s
b1000000100110101 x
b1000000100110101 L
b1000000100110101 P
b1000000100110101 [
b1000000100110101 `
b1000000100110101 Q
b1000000100110101 U
b1000000100110101 W
b1100000010011010 V
b1000000100110101 ?
b1000000100110101 F
b1100000010011010 G
b1000000100110101 4
b1000000100110101 =
b1000000100110101 I
b1000000100110101 N
b1000000100110101 S
b1000000100110101 >
b1000000100110101 B
b1000000100110101 D
b1100000010011010 C
b1100000010011010 9
b1000000100110101 3
b1000000100110101 8
b1000000100110101 ;
b1000000100110101 @
b101 +
b1000000100110101 %
b1000000100110101 .
b1000000100110101 6
1*
1"
#550
0*
0"
#600
b1110000001001101 !"
b1100000010011011 v
b1100000010011011 z
b1100000010011011 |
b1000000100110110 _
b1000000100110110 f
b1100000010011011 g
b1100000010011011 {
b1000000100110110 M
b1000000100110110 ]
b1000000100110110 ^
b1000000100110110 b
b1000000100110110 d
b1100000010011011 c
b1000000100110110 R
b1000000100110110 Y
b1100000010011011 Z
b1000000100110110 2
b1000000100110110 K
b1000000100110110 i
b1000000100110110 n
b1000000100110110 s
b1000000100110110 x
b1000000100110110 L
b1000000100110110 P
b1000000100110110 [
b1000000100110110 `
b1000000100110110 Q
b1000000100110110 U
b1000000100110110 W
b1100000010011011 V
b1000000100110110 ?
b1000000100110110 F
b1100000010011011 G
b1000000100110110 4
b1000000100110110 =
b1000000100110110 I
b1000000100110110 N
b1000000100110110 S
b1000000100110110 >
b1000000100110110 B
b1000000100110110 D
b1100000010011011 C
b1100000010011011 9
b1000000100110110 3
b1000000100110110 8
b1000000100110110 ;
b1000000100110110 @
b110 +
b1000000100110110 %
b1000000100110110 .
b1000000100110110 6
1*
1"
#650
0*
0"
#700
b1000000100110111 _
b1000000100110111 f
b1100000010011011 g
b1100000010011011 {
b1000000100110111 M
b1000000100110111 ]
b1000000100110111 ^
b1000000100110111 b
b1000000100110111 d
b1100000010011011 c
b1000000100110111 R
b1000000100110111 Y
b1100000010011011 Z
b1000000100110111 2
b1000000100110111 K
b1000000100110111 i
b1000000100110111 n
b1000000100110111 s
b1000000100110111 x
b1000000100110111 L
b1000000100110111 P
b1000000100110111 [
b1000000100110111 `
b1000000100110111 Q
b1000000100110111 U
b1000000100110111 W
b1100000010011011 V
b1000000100110111 ?
b1000000100110111 F
b1100000010011011 G
b1000000100110111 4
b1000000100110111 =
b1000000100110111 I
b1000000100110111 N
b1000000100110111 S
b1000000100110111 >
b1000000100110111 B
b1000000100110111 D
b1100000010011011 C
b1100000010011011 9
b1000000100110111 3
b1000000100110111 8
b1000000100110111 ;
b1000000100110111 @
b111 +
b1000000100110111 %
b1000000100110111 .
b1000000100110111 6
1*
1"
#750
0*
0"
#800
b1111100000010011 ."
b1111000000100111 %"
b1111000000100111 )"
b1111000000100111 +"
b1111000000100111 *"
b1110000001001110 q
b1110000001001110 u
b1110000001001110 ""
b1110000001001110 '"
b1110000001001110 w
b1110000001001110 ~
b1110000001001110 !"
b1100000010011100 v
b1100000010011100 z
b1100000010011100 |
b1000000100111000 _
b1000000100111000 f
b1100000010011100 g
b1100000010011100 {
b1000000100111000 M
b1000000100111000 ]
b1000000100111000 ^
b1000000100111000 b
b1000000100111000 d
b1100000010011100 c
b1000000100111000 R
b1000000100111000 Y
b1100000010011100 Z
b1000000100111000 2
b1000000100111000 K
b1000000100111000 i
b1000000100111000 n
b1000000100111000 s
b1000000100111000 x
b1000000100111000 L
b1000000100111000 P
b1000000100111000 [
b1000000100111000 `
b1000000100111000 Q
b1000000100111000 U
b1000000100111000 W
b1100000010011100 V
b1000000100111000 ?
b1000000100111000 F
b1100000010011100 G
b1000000100111000 4
b1000000100111000 =
b1000000100111000 I
b1000000100111000 N
b1000000100111000 S
b1000000100111000 >
b1000000100111000 B
b1000000100111000 D
b1100000010011100 C
b1100000010011100 9
b1000000100111000 3
b1000000100111000 8
b1000000100111000 ;
b1000000100111000 @
b1000 +
b1000000100111000 %
b1000000100111000 .
b1000000100111000 6
1*
1"
#850
0*
0"
#900
b1000000100111001 _
b1000000100111001 f
b1100000010011100 g
b1100000010011100 {
b1000000100111001 M
b1000000100111001 ]
b1000000100111001 ^
b1000000100111001 b
b1000000100111001 d
b1100000010011100 c
b1000000100111001 R
b1000000100111001 Y
b1100000010011100 Z
b1000000100111001 2
b1000000100111001 K
b1000000100111001 i
b1000000100111001 n
b1000000100111001 s
b1000000100111001 x
b1000000100111001 L
b1000000100111001 P
b1000000100111001 [
b1000000100111001 `
b1000000100111001 Q
b1000000100111001 U
b1000000100111001 W
b1100000010011100 V
b1000000100111001 ?
b1000000100111001 F
b1100000010011100 G
b1000000100111001 4
b1000000100111001 =
b1000000100111001 I
b1000000100111001 N
b1000000100111001 S
b1000000100111001 >
b1000000100111001 B
b1000000100111001 D
b1100000010011100 C
b1100000010011100 9
b1000000100111001 3
b1000000100111001 8
b1000000100111001 ;
b1000000100111001 @
b1001 +
b1000000100111001 %
b1000000100111001 .
b1000000100111001 6
1*
1"
#950
0*
0"
#1000
b1110000001001110 !"
b1100000010011101 v
b1100000010011101 z
b1100000010011101 |
b1000000100111010 _
b1000000100111010 f
b1100000010011101 g
b1100000010011101 {
b1000000100111010 M
b1000000100111010 ]
b1000000100111010 ^
b1000000100111010 b
b1000000100111010 d
b1100000010011101 c
b1000000100111010 R
b1000000100111010 Y
b1100000010011101 Z
b1000000100111010 2
b1000000100111010 K
b1000000100111010 i
b1000000100111010 n
b1000000100111010 s
b1000000100111010 x
b1000000100111010 L
b1000000100111010 P
b1000000100111010 [
b1000000100111010 `
b1000000100111010 Q
b1000000100111010 U
b1000000100111010 W
b1100000010011101 V
b1000000100111010 ?
b1000000100111010 F
b1100000010011101 G
b1000000100111010 4
b1000000100111010 =
b1000000100111010 I
b1000000100111010 N
b1000000100111010 S
b1000000100111010 >
b1000000100111010 B
b1000000100111010 D
b1100000010011101 C
b1100000010011101 9
b1000000100111010 3
b1000000100111010 8
b1000000100111010 ;
b1000000100111010 @
b1010 +
b1000000100111010 %
b1000000100111010 .
b1000000100111010 6
1*
1"
#1050
0*
0"
#1100
b1000000100111011 _
b1000000100111011 f
b1100000010011101 g
b1100000010011101 {
b1000000100111011 M
b1000000100111011 ]
b1000000100111011 ^
b1000000100111011 b
b1000000100111011 d
b1100000010011101 c
b1000000100111011 R
b1000000100111011 Y
b1100000010011101 Z
b1000000100111011 2
b1000000100111011 K
b1000000100111011 i
b1000000100111011 n
b1000000100111011 s
b1000000100111011 x
b1000000100111011 L
b1000000100111011 P
b1000000100111011 [
b1000000100111011 `
b1000000100111011 Q
b1000000100111011 U
b1000000100111011 W
b1100000010011101 V
b1000000100111011 ?
b1000000100111011 F
b1100000010011101 G
b1000000100111011 4
b1000000100111011 =
b1000000100111011 I
b1000000100111011 N
b1000000100111011 S
b1000000100111011 >
b1000000100111011 B
b1000000100111011 D
b1100000010011101 C
b1100000010011101 9
b1000000100111011 3
b1000000100111011 8
b1000000100111011 ;
b1000000100111011 @
b1011 +
b1000000100111011 %
b1000000100111011 .
b1000000100111011 6
1*
1"
